sigma_agent_sdk/__init__.py
sigma_agent_sdk/api_base.py
sigma_agent_sdk/base.py
sigma_agent_sdk/message.py
sigma_agent_sdk/react_base_agent.py
sigma_agent_sdk/react_prompt.py
sigma_agent_sdk/tools.py
sigma_agent_sdk/utils.py
sigma_agent_sdk-0.1.0.dist-info/METADATA
sigma_agent_sdk-0.1.0.dist-info/WHEEL
sigma_agent_sdk-0.1.0.dist-info/RECORD
